{"impurity_orbital": 5, "vqe_depth": 2, "optimizer": "BFGS", "conv_tol": 1e-06, "max_iters": 1000000.0, "gtol": 5e-05, "degenerate": false, "exact_ground_state": -19.86253105231741, "exact_charge": 6.0, "exact_spin": 0.0, "exact_nu_minus": 2, "exact_nd_minus": 3, "exact_krylov_dim_minus": 735, "exact_nu_plus": 4, "exact_nd_plus": 3, "exact_krylov_dim_plus": 1225, "local_vqe_success": true, "local_vqe_nfev": 91425, "local_vqe_njev": 1325, "local_vqe_nit": 1288, "local_vqe_nfev_total": 1949334, "local_vqe_njev_total": 28251, "local_vqe_nit_total": 26805, "min_sector_grad_history": "[]", "min_sector_cost_history": "[]", "vqe_egs": -19.849544379850347, "vqe_charge_result": 6, "vqe_spin_result": 0, "vqe_nu": 3, "vqe_nd": 3, "gs_gtol": 4.999999999999999e-05, "vqe_ground_state_overlap": 0.9992283602760879, "egs_rel_error": 0.0006538276734650932, "gs_error": 0.0007716397239121431, "n_sites": 7, "wall_clock_time": 11982.225550889969, "seed": 65, "target_error": 0.01, "overall_success": true}