{"impurity_orbital": 0, "vqe_depth": 2, "optimizer": "BFGS", "conv_tol": 1e-06, "max_iters": 1000000.0, "gtol": 5e-05, "degenerate": false, "exact_ground_state": -14.22778415591097, "exact_charge": 2.0, "exact_spin": -0.0, "exact_nu_minus": 0, "exact_nd_minus": 1, "exact_krylov_dim_minus": 2, "exact_nu_plus": 2, "exact_nd_plus": 1, "exact_krylov_dim_plus": 2, "local_vqe_success": true, "local_vqe_nfev": 680, "local_vqe_njev": 40, "local_vqe_nit": 32, "local_vqe_nfev_total": 1547, "local_vqe_njev_total": 91, "local_vqe_nit_total": 65, "min_sector_grad_history": "[]", "min_sector_cost_history": "[]", "vqe_egs": -14.227784144772858, "vqe_charge_result": 2, "vqe_spin_result": 0, "vqe_nu": 1, "vqe_nd": 1, "gs_gtol": 0.0005, "vqe_ground_state_overlap": 0.9999999994237567, "egs_rel_error": 7.828422722749315e-10, "gs_error": 5.762432753186886e-10, "n_sites": 2, "wall_clock_time": 0.8832876682281494, "seed": 149, "target_error": 0.0001, "overall_success": true}