{"impurity_orbital": 4, "vqe_depth": 1, "optimizer": "BFGS", "conv_tol": 1e-06, "max_iters": 1000000.0, "gtol": 5e-05, "degenerate": false, "exact_ground_state": -39.081943797380525, "exact_charge": 10.0, "exact_spin": 0.0, "exact_nu_minus": 4, "exact_nd_minus": 5, "exact_krylov_dim_minus": 90, "exact_nu_plus": 6, "exact_nd_plus": 5, "exact_krylov_dim_plus": 6, "local_vqe_success": true, "local_vqe_nfev": 1800, "local_vqe_njev": 60, "local_vqe_nit": 54, "local_vqe_nfev_total": 80190, "local_vqe_njev_total": 2673, "local_vqe_nit_total": 2217, "min_sector_grad_history": "[]", "min_sector_cost_history": "[]", "vqe_egs": -39.04427943992944, "vqe_charge_result": 10, "vqe_spin_result": 0, "vqe_nu": 5, "vqe_nd": 5, "gs_gtol": 0.0005, "vqe_ground_state_overlap": 0.9991936718803028, "egs_rel_error": 0.000963727844407001, "gs_error": 0.0008063281196971639, "n_sites": 6, "wall_clock_time": 259.8661732673645, "seed": 7, "target_error": 0.001, "overall_success": true}