{"impurity_orbital": 5, "vqe_depth": 4, "optimizer": "BFGS", "conv_tol": 1e-06, "max_iters": 1000000.0, "gtol": 5e-05, "degenerate": false, "exact_ground_state": -19.206859740417848, "exact_charge": 8.0, "exact_spin": 0.0, "exact_nu_minus": 3, "exact_nd_minus": 4, "exact_krylov_dim_minus": 1225, "exact_nu_plus": 5, "exact_nd_plus": 4, "exact_krylov_dim_plus": 735, "local_vqe_success": true, "local_vqe_nfev": 62609, "local_vqe_njev": 457, "local_vqe_nit": 452, "local_vqe_nfev_total": 4819660, "local_vqe_njev_total": 35180, "local_vqe_nit_total": 34325, "min_sector_grad_history": "[]", "min_sector_cost_history": "[]", "vqe_egs": -19.197211550922354, "vqe_charge_result": 8, "vqe_spin_result": 0, "vqe_nu": 4, "vqe_nd": 4, "gs_gtol": 0.0005, "vqe_ground_state_overlap": 0.9996576379209793, "egs_rel_error": 0.0005023303978833294, "gs_error": 0.00034236207902071936, "n_sites": 7, "wall_clock_time": 96529.47273302078, "seed": 8, "target_error": 0.001, "overall_success": true}